Workbook

Sheet Premissas
A1: VendeZap — Premissas (células amarelas com texto azul são editáveis)
A2: Preços conferidos em 16/10/2026 em fontes secundárias. Confirme nas páginas oficiais antes de decidir.
A4: Premissa | B4: Valor | C4: Origem / observação
A5: Câmbio (R$ por US$) | B5: 5.15 | C5: Meelion, 16/09/2026 — confira no Banco Central (PTAX)
A6: OpenAI: preço entrada (US$ por 1 milhão de tokens) | B6: 0.25 | C6: gpt-5-mini, fontes secundárias out/2026
A7: OpenAI: preço saída (US$ por 1 milhão de tokens) | B7: 2 | C7: gpt-5-mini; saída inclui tokens de raciocínio
A8: Mensagens do cliente por conversa | B8: 6 | C8: premissa — meça no piloto
A9: Tokens de entrada por resposta da IA | B9: 2000 | C9: instruções + dados do negócio + histórico
A10: Tokens de saída por resposta da IA | B10: 350 | C10: texto da resposta + raciocínio interno
A11: WhatsApp: preço por mensagem de serviço (R$) | B11: 0.035 | C11: Cloud API Brasil, desde 01/10/2026
A12: WhatsApp: mensagens de serviço grátis por número/mês | B12: 1000 | C12: franquia por número
A13: Dias de funcionamento por mês | B13: 30
A14: Imposto sobre a receita (%) | B14: 0.06 | C14: estimativa Simples Nacional — confirme com contador
A15: Taxa por cobrança (R$) | B15: 2 | C15: estimativa — depende do banco/gateway
A16: Domínio por mês (R$) | B16: 3.33 | C16: .com.br ≈ R$ 40/ano (confirme no Registro.br)
A17: VPS até 10 clientes (R$/mês) | B17: 59.99 | C17: Hostinger KVM 1, preço de renovação
A18: VPS de 11 a 30 clientes (R$/mês) | B18: 77.99 | C18: Hostinger KVM 2, preço de renovação
A19: VPS acima de 30 clientes (R$/mês) | B19: 155.98 | C19: 2× KVM 2 (estimativa)
A20: Contador a partir de 6 clientes (R$/mês) | B20: 200 | C20: estimativa
A21: Quanto vale 1 hora sua (R$) | B21: 30 | C21: edite com o seu valor
A23: Custo de IA por conversa (R$) — calculado | B23: =Premissas!$B$8*(Premissas!$B$9*Premissas!$B$6+Premissas!$B$10*Premissas!$B$7)/1000000*Premissas!$B$5

Sheet Custo por cliente
A1: Custo de uso de UM cliente por mês (IA + WhatsApp oficial)
A3: Conversas por dia | B3: Respostas da IA (msgs) por conversa | C3: Conversas no mês | D3: Custo IA (R$) | E3: Mensagens enviadas | F3: Mensagens pagas (acima da franquia) | G3: Custo WhatsApp (R$) | H3: Total (R$)
A4: 10 | B4: 3 | C4: =A4*Premissas!$B$13 | D4: =C4*Premissas!$B$23 | E4: =C4*B4 | F4: =MAX(0,E4-Premissas!$B$12) | G4: =F4*Premissas!$B$11 | H4: =D4+G4
A5: 15 | B5: 3 | C5: =A5*Premissas!$B$13 | D5: =C5*Premissas!$B$23 | E5: =C5*B5 | F5: =MAX(0,E5-Premissas!$B$12) | G5: =F5*Premissas!$B$11 | H5: =D5+G5
A6: 20 | B6: 4 | C6: =A6*Premissas!$B$13 | D6: =C6*Premissas!$B$23 | E6: =C6*B6 | F6: =MAX(0,E6-Premissas!$B$12) | G6: =F6*Premissas!$B$11 | H6: =D6+G6
A7: 50 | B7: 4 | C7: =A7*Premissas!$B$13 | D7: =C7*Premissas!$B$23 | E7: =C7*B7 | F7: =MAX(0,E7-Premissas!$B$12) | G7: =F7*Premissas!$B$11 | H7: =D7+G7
A8: 100 | B8: 4 | C8: =A8*Premissas!$B$13 | D8: =C8*Premissas!$B$23 | E8: =C8*B8 | F8: =MAX(0,E8-Premissas!$B$12) | G8: =F8*Premissas!$B$11 | H8: =D8+G8
A10: Com a ponte não oficial (QR Code) o custo do WhatsApp por mensagem é R$ 0 — mas há risco de bloqueio do número.

Sheet Cenários
A1: Cenários mensais por número de clientes (fórmulas ligadas às Premissas)
A2: Taxa de implantação (setup) é receita única e NÃO entra nesta tabela mensal.
A4: Cenário Conservador
A5: Mensalidade por cliente (R$) | B5: 97
A6: Conversas por dia por cliente | B6: 20
A7: Respostas da IA por conversa | B7: 4
A8: Horas suas por cliente/mês | B8: 1.5
A9: Taxa de implantação (R$, única) | B9: 0
A11: Clientes | B11: Receita | C11: IA | D11: WhatsApp | E11: Cobranças | F11: Servidor + domínio | G11: Lucro bruto | H11: Impostos | I11: Contador | J11: Lucro operacional | K11: Horas suas/mês | L11: Lucro − valor do seu tempo
A12: 1 | B12: =A12*$B$5 | C12: =A12*$B$6*Premissas!$B$13*Premissas!$B$23 | D12: =A12*MAX(0,$B$6*Premissas!$B$13*$B$7-Premissas!$B$12)*Premissas!$B$11 | E12: =A12*Premissas!$B$15 | F12: =IF(A12<=10,Premissas!$B$17,IF(A12<=30,Premissas!$B$18,Premissas!$B$19))+Premissas!$B$16 | G12: =B12-C12-D12-E12-F12 | H12: =B12*Premissas!$B$14 | I12: =IF(A12<=5,0,Premissas!$B$20) | J12: =G12-H12-I12 | K12: =A12*$B$8 | L12: =J12-K12*Premissas!$B$21
A13: 5 | B13: =A13*$B$5 | C13: =A13*$B$6*Premissas!$B$13*Premissas!$B$23 | D13: =A13*MAX(0,$B$6*Premissas!$B$13*$B$7-Premissas!$B$12)*Premissas!$B$11 | E13: =A13*Premissas!$B$15 | F13: =IF(A13<=10,Premissas!$B$17,IF(A13<=30,Premissas!$B$18,Premissas!$B$19))+Premissas!$B$16 | G13: =B13-C13-D13-E13-F13 | H13: =B13*Premissas!$B$14 | I13: =IF(A13<=5,0,Premissas!$B$20) | J13: =G13-H13-I13 | K13: =A13*$B$8 | L13: =J13-K13*Premissas!$B$21
A14: 10 | B14: =A14*$B$5 | C14: =A14*$B$6*Premissas!$B$13*Premissas!$B$23 | D14: =A14*MAX(0,$B$6*Premissas!$B$13*$B$7-Premissas!$B$12)*Premissas!$B$11 | E14: =A14*Premissas!$B$15 | F14: =IF(A14<=10,Premissas!$B$17,IF(A14<=30,Premissas!$B$18,Premissas!$B$19))+Premissas!$B$16 | G14: =B14-C14-D14-E14-F14 | H14: =B14*Premissas!$B$14 | I14: =IF(A14<=5,0,Premissas!$B$20) | J14: =G14-H14-I14 | K14: =A14*$B$8 | L14: =J14-K14*Premissas!$B$21
A15: 25 | B15: =A15*$B$5 | C15: =A15*$B$6*Premissas!$B$13*Premissas!$B$23 | D15: =A15*MAX(0,$B$6*Premissas!$B$13*$B$7-Premissas!$B$12)*Premissas!$B$11 | E15: =A15*Premissas!$B$15 | F15: =IF(A15<=10,Premissas!$B$17,IF(A15<=30,Premissas!$B$18,Premissas!$B$19))+Premissas!$B$16 | G15: =B15-C15-D15-E15-F15 | H15: =B15*Premissas!$B$14 | I15: =IF(A15<=5,0,Premissas!$B$20) | J15: =G15-H15-I15 | K15: =A15*$B$8 | L15: =J15-K15*Premissas!$B$21
A16: 50 | B16: =A16*$B$5 | C16: =A16*$B$6*Premissas!$B$13*Premissas!$B$23 | D16: =A16*MAX(0,$B$6*Premissas!$B$13*$B$7-Premissas!$B$12)*Premissas!$B$11 | E16: =A16*Premissas!$B$15 | F16: =IF(A16<=10,Premissas!$B$17,IF(A16<=30,Premissas!$B$18,Premissas!$B$19))+Premissas!$B$16 | G16: =B16-C16-D16-E16-F16 | H16: =B16*Premissas!$B$14 | I16: =IF(A16<=5,0,Premissas!$B$20) | J16: =G16-H16-I16 | K16: =A16*$B$8 | L16: =J16-K16*Premissas!$B$21
A19: Cenário Base
A20: Mensalidade por cliente (R$) | B20: 147
A21: Conversas por dia por cliente | B21: 15
A22: Respostas da IA por conversa | B22: 3
A23: Horas suas por cliente/mês | B23: 1
A24: Taxa de implantação (R$, única) | B24: 197
A26: Clientes | B26: Receita | C26: IA | D26: WhatsApp | E26: Cobranças | F26: Servidor + domínio | G26: Lucro bruto | H26: Impostos | I26: Contador | J26: Lucro operacional | K26: Horas suas/mês | L26: Lucro − valor do seu tempo
A27: 1 | B27: =A27*$B$20 | C27: =A27*$B$21*Premissas!$B$13*Premissas!$B$23 | D27: =A27*MAX(0,$B$21*Premissas!$B$13*$B$22-Premissas!$B$12)*Premissas!$B$11 | E27: =A27*Premissas!$B$15 | F27: =IF(A27<=10,Premissas!$B$17,IF(A27<=30,Premissas!$B$18,Premissas!$B$19))+Premissas!$B$16 | G27: =B27-C27-D27-E27-F27 | H27: =B27*Premissas!$B$14 | I27: =IF(A27<=5,0,Premissas!$B$20) | J27: =G27-H27-I27 | K27: =A27*$B$23 | L27: =J27-K27*Premissas!$B$21
A28: 5 | B28: =A28*$B$20 | C28: =A28*$B$21*Premissas!$B$13*Premissas!$B$23 | D28: =A28*MAX(0,$B$21*Premissas!$B$13*$B$22-Premissas!$B$12)*Premissas!$B$11 | E28: =A28*Premissas!$B$15 | F28: =IF(A28<=10,Premissas!$B$17,IF(A28<=30,Premissas!$B$18,Premissas!$B$19))+Premissas!$B$16 | G28: =B28-C28-D28-E28-F28 | H28: =B28*Premissas!$B$14 | I28: =IF(A28<=5,0,Premissas!$B$20) | J28: =G28-H28-I28 | K28: =A28*$B$23 | L28: =J28-K28*Premissas!$B$21
A29: 10 | B29: =A29*$B$20 | C29: =A29*$B$21*Premissas!$B$13*Premissas!$B$23 | D29: =A29*MAX(0,$B$21*Premissas!$B$13*$B$22-Premissas!$B$12)*Premissas!$B$11 | E29: =A29*Premissas!$B$15 | F29: =IF(A29<=10,Premissas!$B$17,IF(A29<=30,Premissas!$B$18,Premissas!$B$19))+Premissas!$B$16 | G29: =B29-C29-D29-E29-F29 | H29: =B29*Premissas!$B$14 | I29: =IF(A29<=5,0,Premissas!$B$20) | J29: =G29-H29-I29 | K29: =A29*$B$23 | L29: =J29-K29*Premissas!$B$21
A30: 25 | B30: =A30*$B$20 | C30: =A30*$B$21*Premissas!$B$13*Premissas!$B$23 | D30: =A30*MAX(0,$B$21*Premissas!$B$13*$B$22-Premissas!$B$12)*Premissas!$B$11 | E30: =A30*Premissas!$B$15 | F30: =IF(A30<=10,Premissas!$B$17,IF(A30<=30,Premissas!$B$18,Premissas!$B$19))+Premissas!$B$16 | G30: =B30-C30-D30-E30-F30 | H30: =B30*Premissas!$B$14 | I30: =IF(A30<=5,0,Premissas!$B$20) | J30: =G30-H30-I30 | K30: =A30*$B$23 | L30: =J30-K30*Premissas!$B$21
A31: 50 | B31: =A31*$B$20 | C31: =A31*$B$21*Premissas!$B$13*Premissas!$B$23 | D31: =A31*MAX(0,$B$21*Premissas!$B$13*$B$22-Premissas!$B$12)*Premissas!$B$11 | E31: =A31*Premissas!$B$15 | F31: =IF(A31<=10,Premissas!$B$17,IF(A31<=30,Premissas!$B$18,Premissas!$B$19))+Premissas!$B$16 | G31: =B31-C31-D31-E31-F31 | H31: =B31*Premissas!$B$14 | I31: =IF(A31<=5,0,Premissas!$B$20) | J31: =G31-H31-I31 | K31: =A31*$B$23 | L31: =J31-K31*Premissas!$B$21
A34: Cenário Otimista
A35: Mensalidade por cliente (R$) | B35: 197
A36: Conversas por dia por cliente | B36: 12
A37: Respostas da IA por conversa | B37: 3
A38: Horas suas por cliente/mês | B38: 0.75
A39: Taxa de implantação (R$, única) | B39: 297
A41: Clientes | B41: Receita | C41: IA | D41: WhatsApp | E41: Cobranças | F41: Servidor + domínio | G41: Lucro bruto | H41: Impostos | I41: Contador | J41: Lucro operacional | K41: Horas suas/mês | L41: Lucro − valor do seu tempo
A42: 1 | B42: =A42*$B$35 | C42: =A42*$B$36*Premissas!$B$13*Premissas!$B$23 | D42: =A42*MAX(0,$B$36*Premissas!$B$13*$B$37-Premissas!$B$12)*Premissas!$B$11 | E42: =A42*Premissas!$B$15 | F42: =IF(A42<=10,Premissas!$B$17,IF(A42<=30,Premissas!$B$18,Premissas!$B$19))+Premissas!$B$16 | G42: =B42-C42-D42-E42-F42 | H42: =B42*Premissas!$B$14 | I42: =IF(A42<=5,0,Premissas!$B$20) | J42: =G42-H42-I42 | K42: =A42*$B$38 | L42: =J42-K42*Premissas!$B$21
A43: 5 | B43: =A43*$B$35 | C43: =A43*$B$36*Premissas!$B$13*Premissas!$B$23 | D43: =A43*MAX(0,$B$36*Premissas!$B$13*$B$37-Premissas!$B$12)*Premissas!$B$11 | E43: =A43*Premissas!$B$15 | F43: =IF(A43<=10,Premissas!$B$17,IF(A43<=30,Premissas!$B$18,Premissas!$B$19))+Premissas!$B$16 | G43: =B43-C43-D43-E43-F43 | H43: =B43*Premissas!$B$14 | I43: =IF(A43<=5,0,Premissas!$B$20) | J43: =G43-H43-I43 | K43: =A43*$B$38 | L43: =J43-K43*Premissas!$B$21
A44: 10 | B44: =A44*$B$35 | C44: =A44*$B$36*Premissas!$B$13*Premissas!$B$23 | D44: =A44*MAX(0,$B$36*Premissas!$B$13*$B$37-Premissas!$B$12)*Premissas!$B$11 | E44: =A44*Premissas!$B$15 | F44: =IF(A44<=10,Premissas!$B$17,IF(A44<=30,Premissas!$B$18,Premissas!$B$19))+Premissas!$B$16 | G44: =B44-C44-D44-E44-F44 | H44: =B44*Premissas!$B$14 | I44: =IF(A44<=5,0,Premissas!$B$20) | J44: =G44-H44-I44 | K44: =A44*$B$38 | L44: =J44-K44*Premissas!$B$21
A45: 25 | B45: =A45*$B$35 | C45: =A45*$B$36*Premissas!$B$13*Premissas!$B$23 | D45: =A45*MAX(0,$B$36*Premissas!$B$13*$B$37-Premissas!$B$12)*Premissas!$B$11 | E45: =A45*Premissas!$B$15 | F45: =IF(A45<=10,Premissas!$B$17,IF(A45<=30,Premissas!$B$18,Premissas!$B$19))+Premissas!$B$16 | G45: =B45-C45-D45-E45-F45 | H45: =B45*Premissas!$B$14 | I45: =IF(A45<=5,0,Premissas!$B$20) | J45: =G45-H45-I45 | K45: =A45*$B$38 | L45: =J45-K45*Premissas!$B$21
A46: 50 | B46: =A46*$B$35 | C46: =A46*$B$36*Premissas!$B$13*Premissas!$B$23 | D46: =A46*MAX(0,$B$36*Premissas!$B$13*$B$37-Premissas!$B$12)*Premissas!$B$11 | E46: =A46*Premissas!$B$15 | F46: =IF(A46<=10,Premissas!$B$17,IF(A46<=30,Premissas!$B$18,Premissas!$B$19))+Premissas!$B$16 | G46: =B46-C46-D46-E46-F46 | H46: =B46*Premissas!$B$14 | I46: =IF(A46<=5,0,Premissas!$B$20) | J46: =G46-H46-I46 | K46: =A46*$B$38 | L46: =J46-K46*Premissas!$B$21

Sheet Sua 1 hora por dia
A1: Quantos clientes cabem em 1 hora por dia?
A3: Horas disponíveis por mês | B3: 30
A4: Horas de suporte por cliente/mês | B4: 1
A5: Horas para implantar 1 cliente novo (única) | B5: 5
A6: Clientes novos por mês | B6: 2
A7: Horas de prospecção por mês | B7: 6
A9: Horas que sobram para suporte | B9: =B3-B5*B6-B7
A10: Máximo de clientes que você consegue atender | B10: =ROUNDDOWN(B9/B4,0)
A12: Acima disso: automatize o suporte, aumente o preço ou delegue (ver guia, fase 13).
